nbprint/__init__.py
nbprint/__main__.py
nbprint/cli.py
nbprint/config/__init__.py
nbprint/config/base.py
nbprint/config/exceptions.py
nbprint/config/page.py
nbprint/config/common/__init__.py
nbprint/config/common/border.py
nbprint/config/common/common.py
nbprint/config/common/css.py
nbprint/config/common/display.py
nbprint/config/common/page.py
nbprint/config/common/spacing.py
nbprint/config/common/style.py
nbprint/config/common/text.py
nbprint/config/content/__init__.py
nbprint/config/content/base.py
nbprint/config/content/common.py
nbprint/config/content/cover.py
nbprint/config/content/image.py
nbprint/config/content/page.py
nbprint/config/content/pagebreak.py
nbprint/config/content/table_of_contents.py
nbprint/config/core/__init__.py
nbprint/config/core/config.py
nbprint/config/core/content.py
nbprint/config/core/context.py
nbprint/config/core/outputs.py
nbprint/config/core/parameters.py
nbprint/config/hydra/__init__.py
nbprint/config/hydra/base.yaml
nbprint/config/hydra/hydra/hydra_logging/custom.yaml
nbprint/config/hydra/hydra/job_logging/custom.yaml
nbprint/config/hydra/nbprint/content/frontmatter/nbprint/title.yaml
nbprint/config/hydra/nbprint/content/frontmatter/nbprint/title_toc.yaml
nbprint/config/hydra/nbprint/content/frontmatter/nbprint/toc.yaml
nbprint/config/hydra/nbprint/nbprint/default.yaml
nbprint/config/hydra/nbprint/outputs/nbprint/default.yaml
nbprint/config/hydra/nbprint/outputs/nbprint/email.yaml
nbprint/config/hydra/nbprint/outputs/nbprint/pdf.yaml
nbprint/config/hydra/nbprint/page/nbprint/default.yaml
nbprint/config/hydra/nbprint/parameters/nbprint/papermill.yaml
nbprint/config/outputs/__init__.py
nbprint/config/outputs/email.py
nbprint/config/outputs/nbconvert.py
nbprint/example/__init__.py
nbprint/example/basic/__init__.py
nbprint/example/basic/code.py
nbprint/example/basic/context.py
nbprint/example/basic/cover.py
nbprint/example/basic/markdown.py
nbprint/example/basic/page.py
nbprint/example/basic/parameters.py
nbprint-0.10.0.dist-info/METADATA
nbprint-0.10.0.dist-info/WHEEL
nbprint-0.10.0.dist-info/entry_points.txt
nbprint-0.10.0.dist-info/licenses/LICENSE
nbprint-0.10.0.dist-info/RECORD
