Metadata-Version: 2.4
Name: nbprint
Version: 0.10.0
Summary: A framework for customizing NBConvert templates and building reports
Project-URL: Repository, https://github.com/nbprint/nbprint
Project-URL: Homepage, https://github.com/nbprint/nbprint
Author-email: the nbprint authors <t.paine154@gmail.com>
License: Apache-2.0
License-File: LICENSE
Keywords: Jupyter,JupyterLab,Notebook,Notebooks,Report,Reporting,Reports
Classifier: Development Status :: 4 - Beta
Classifier: Framework :: Jupyter
Classifier: Framework :: Jupyter :: JupyterLab
Classifier: License :: OSI Approved :: Apache Software License
Classifier: Programming Language :: Python
Classifier: Programming Language :: Python :: 3
Classifier: Programming Language :: Python :: 3.10
Classifier: Programming Language :: Python :: 3.11
Classifier: Programming Language :: Python :: 3.12
Classifier: Programming Language :: Python :: 3.13
Classifier: Programming Language :: Python :: 3.14
Classifier: Programming Language :: Python :: Implementation :: CPython
Classifier: Programming Language :: Python :: Implementation :: PyPy
Requires-Python: >=3.10
Requires-Dist: ccflow>=0.4.0
Requires-Dist: dominate
Requires-Dist: emails
Requires-Dist: hydra-core
Requires-Dist: ipywidgets
Requires-Dist: jinja2
Requires-Dist: lerna>=1.1.0
Requires-Dist: nbconvert[webpdf]>=7.11.0
Requires-Dist: nbformat
Requires-Dist: notebook
Requires-Dist: omegaconf
Requires-Dist: pydantic-extra-types
Requires-Dist: pydantic<3,>=2
Requires-Dist: strenum
Requires-Dist: typer
Requires-Dist: typing-extensions
Provides-Extra: develop
Requires-Dist: build; extra == 'develop'
Requires-Dist: bump-my-version; extra == 'develop'
Requires-Dist: check-manifest; extra == 'develop'
Requires-Dist: codespell<2.5,>=2.4; extra == 'develop'
Requires-Dist: great-tables; extra == 'develop'
Requires-Dist: hatch-js; extra == 'develop'
Requires-Dist: hatchling; extra == 'develop'
Requires-Dist: matplotlib; extra == 'develop'
Requires-Dist: mdformat-tables>=1; extra == 'develop'
Requires-Dist: mdformat<1.1,>=0.7.22; extra == 'develop'
Requires-Dist: nbprint-example-plugin; extra == 'develop'
Requires-Dist: pandas; extra == 'develop'
Requires-Dist: perspective-python>=3; extra == 'develop'
Requires-Dist: plotly; extra == 'develop'
Requires-Dist: pyarrow; extra == 'develop'
Requires-Dist: pytest; extra == 'develop'
Requires-Dist: pytest-cov; extra == 'develop'
Requires-Dist: ruff<0.15,>=0.9; extra == 'develop'
Requires-Dist: seaborn; extra == 'develop'
Requires-Dist: superstore; extra == 'develop'
Requires-Dist: twine; extra == 'develop'
Requires-Dist: wheel; extra == 'develop'
